gitllama/__init__.py
gitllama/cli.py
gitllama/config.py
gitllama/ai/README_REPRESENTATIVES.md
gitllama/ai/__init__.py
gitllama/ai/client.py
gitllama/ai/congress.py
gitllama/ai/context_compressor.py
gitllama/ai/parser.py
gitllama/ai/query.py
gitllama/ai/representatives.py
gitllama/core/__init__.py
gitllama/core/coordinator.py
gitllama/core/git_operations.py
gitllama/todo/__init__.py
gitllama/todo/analyzer.py
gitllama/todo/executor.py
gitllama/todo/planner.py
gitllama/utils/__init__.py
gitllama/utils/config.py
gitllama/utils/context_tracker.py
gitllama/utils/metrics.py
gitllama/utils/reports.py
todollama-0.8.0.dist-info/METADATA
todollama-0.8.0.dist-info/WHEEL
todollama-0.8.0.dist-info/entry_points.txt
todollama-0.8.0.dist-info/licenses/LICENSE
todollama-0.8.0.dist-info/RECORD
