Metadata-Version: 2.4
Name: todollama
Version: 0.8.0
Summary: AI-powered Python code generation tool - creates containerized Python applications from TODO.md descriptions
Project-URL: Homepage, https://github.com/your-org/todollama
Project-URL: Repository, https://github.com/your-org/todollama.git
Project-URL: Issues, https://github.com/your-org/todollama/issues
Author-email: Your Name <your.email@example.com>
Maintainer-email: Your Name <your.email@example.com>
License: GPL-3.0-or-later
License-File: LICENSE
Keywords: ai,code-generation,containerization,llm,ollama,python,todo
Classifier: Development Status :: 3 - Alpha
Classifier: Intended Audience :: Developers
Classifier: License :: OSI Approved :: GNU General Public License v3 or later (GPLv3+)
Classifier: Operating System :: OS Independent
Classifier: Programming Language :: Python
Classifier: Programming Language :: Python :: 3
Classifier: Programming Language :: Python :: 3.8
Classifier: Programming Language :: Python :: 3.9
Classifier: Programming Language :: Python :: 3.10
Classifier: Programming Language :: Python :: 3.11
Classifier: Programming Language :: Python :: 3.12
Classifier: Topic :: Software Development :: Libraries :: Python Modules
Classifier: Topic :: Software Development :: Version Control :: Git
Requires-Python: >=3.8
Requires-Dist: importlib-metadata>=1.0.0; python_version < '3.8'
Requires-Dist: jinja2>=3.1.0
Requires-Dist: pygments>=2.15.0
Requires-Dist: requests>=2.31.0
Provides-Extra: dev
Requires-Dist: black>=23.0.0; extra == 'dev'
Requires-Dist: flake8>=6.0.0; extra == 'dev'
Requires-Dist: mypy>=1.0.0; extra == 'dev'
Requires-Dist: pre-commit>=3.0.0; extra == 'dev'
Requires-Dist: pytest-cov>=4.0.0; extra == 'dev'
Requires-Dist: pytest>=7.0.0; extra == 'dev'
Provides-Extra: test
Requires-Dist: pytest-cov>=4.0.0; extra == 'test'
Requires-Dist: pytest>=7.0.0; extra == 'test'
